kpm_tools/__init__.py
kpm_tools/__main__.py
kpm_tools/bloch.py
kpm_tools/common.py
kpm_tools/evolution.py
kpm_tools/hamiltonians.py
kpm_tools/kpm_funcs.py
kpm_tools/kpm_generator.py
kpm_tools/plotting.py
kpm_tools/py.typed
kpm_tools/tiles.py
kpm_tools/utils.py
kpm_tools-0.0.9.dist-info/LICENSE
kpm_tools-0.0.9.dist-info/METADATA
kpm_tools-0.0.9.dist-info/WHEEL
kpm_tools-0.0.9.dist-info/entry_points.txt
kpm_tools-0.0.9.dist-info/RECORD
