Metadata-Version: 2.1
Name: kpm-tools
Version: 0.0.9
Summary: KPM Tools
Home-page: https://github.com/piskunow/kpm-tools
License: BSD 2-Clause
Author: Pablo Piskunow
Author-email: kpm@piskunow.com
Requires-Python: >=3.9,<4.0
Classifier: Development Status :: 4 - Beta
Classifier: License :: Other/Proprietary License
Classifier: Programming Language :: Python :: 3
Classifier: Programming Language :: Python :: 3.9
Classifier: Programming Language :: Python :: 3.10
Classifier: Programming Language :: Python :: 3.11
Classifier: Programming Language :: Python :: 3.12
Provides-Extra: kwant
Requires-Dist: click (>=8.0.1)
Requires-Dist: matplotlib (>=3.8.2,<4.0.0)
Requires-Dist: nox-poetry (>=1.0.3,<2.0.0)
Requires-Dist: numpy (>=1.26.2,<2.0.0)
Requires-Dist: pandoc (>=2.3,<3.0)
Requires-Dist: scipy (>=1.11.4,<2.0.0)
Requires-Dist: tinyarray (>=1.2.4,<2.0.0)
Requires-Dist: tornado (>=6.3.3)
Project-URL: Changelog, https://github.com/piskunow/kpm-tools/releases
Project-URL: Documentation, https://kpm-tools.readthedocs.io
Project-URL: Repository, https://github.com/piskunow/kpm-tools
